keycloak_lib/__init__.py
keycloak_lib/base/__init__.py
keycloak_lib/base/base_client.py
keycloak_lib/base/config.py
keycloak_lib/exceptions/__init__.py
keycloak_lib/exceptions/errors.py
keycloak_lib/sessions/__init__.py
keycloak_lib/sessions/session_manager.py
idp_async_client-0.1.0.dist-info/LICENSE
idp_async_client-0.1.0.dist-info/METADATA
idp_async_client-0.1.0.dist-info/WHEEL
idp_async_client-0.1.0.dist-info/top_level.txt
idp_async_client-0.1.0.dist-info/RECORD
